tidetable/__init__.py
tidetable/tidetable.py
tidetable-0.1.2.dist-info/DESCRIPTION.rst
tidetable-0.1.2.dist-info/entry_points.txt
tidetable-0.1.2.dist-info/METADATA
tidetable-0.1.2.dist-info/metadata.json
tidetable-0.1.2.dist-info/RECORD
tidetable-0.1.2.dist-info/top_level.txt
tidetable-0.1.2.dist-info/WHEEL
