Metadata-Version: 2.0
Name: tidetable
Version: 0.1.2
Summary: Thin API for NOAA tide tables
Home-page: https://github.com/fitnr/tidetable
Author: Neil Freeman
Author-email: contact@fakeisthenewreal.org
License: GPL-3.0
Keywords: noaa
Platform: UNKNOWN
Classifier: Development Status :: 4 - Beta
Classifier: Intended Audience :: Developers
Classifier: License :: OSI Approved :: GNU General Public License v3 (GPLv3)
Classifier: Natural Language :: English
Classifier: Operating System :: Unix
Classifier: Programming Language :: Python :: 2.7
Classifier: Programming Language :: Python :: 3.4
Classifier: Programming Language :: Python :: Implementation :: PyPy
Classifier: Operating System :: OS Independent
Requires-Dist: requests
